sphinx_syntax/__init__.py
sphinx_syntax/_version.py
sphinx_syntax/autodoc.py
sphinx_syntax/diagram.py
sphinx_syntax/domain.py
sphinx_syntax/model.py
sphinx_syntax/model_renderer.py
sphinx_syntax/py.typed
sphinx_syntax/reachable_finder.py
sphinx_syntax/ext/__init__.py
sphinx_syntax/ext/utils.py
sphinx_syntax/ext/antlr4/__init__.py
sphinx_syntax/ext/antlr4/sphinx_a4doc_convert.py
sphinx_syntax/ext/bison/__init__.py
sphinx_syntax/ext/syntax/ANTLRv4Lexer.g4
sphinx_syntax/ext/syntax/ANTLRv4LexerBase.py.in
sphinx_syntax/ext/syntax/ANTLRv4Parser.g4
sphinx_syntax/ext/syntax/BisonLexer.g4
sphinx_syntax/ext/syntax/BisonLexerBase.py.in
sphinx_syntax/ext/syntax/BisonParser.g4
sphinx_syntax/ext/syntax/LexBasic.g4
sphinx_syntax/ext/syntax/__init__.py
sphinx_syntax/ext/syntax/run_gen.py
sphinx_syntax/ext/syntax/gen/ANTLRv4Lexer.interp
sphinx_syntax/ext/syntax/gen/ANTLRv4Lexer.py
sphinx_syntax/ext/syntax/gen/ANTLRv4Lexer.tokens
sphinx_syntax/ext/syntax/gen/ANTLRv4LexerBase.py
sphinx_syntax/ext/syntax/gen/ANTLRv4Parser.interp
sphinx_syntax/ext/syntax/gen/ANTLRv4Parser.py
sphinx_syntax/ext/syntax/gen/ANTLRv4Parser.tokens
sphinx_syntax/ext/syntax/gen/ANTLRv4ParserListener.py
sphinx_syntax/ext/syntax/gen/ANTLRv4ParserVisitor.py
sphinx_syntax/ext/syntax/gen/BisonLexer.interp
sphinx_syntax/ext/syntax/gen/BisonLexer.py
sphinx_syntax/ext/syntax/gen/BisonLexer.tokens
sphinx_syntax/ext/syntax/gen/BisonLexerBase.py
sphinx_syntax/ext/syntax/gen/BisonParser.interp
sphinx_syntax/ext/syntax/gen/BisonParser.py
sphinx_syntax/ext/syntax/gen/BisonParser.tokens
sphinx_syntax/ext/syntax/gen/BisonParserListener.py
sphinx_syntax/ext/syntax/gen/BisonParserVisitor.py
sphinx_syntax/ext/syntax/gen/__init__.py
sphinx_syntax/static/syntax-diagrams-ext.css
sphinx_syntax/static/syntax-diagrams-latex.css
sphinx_syntax/static/syntax-diagrams.css
sphinx_syntax-1.2.0.dist-info/licenses/LICENSE
sphinx_syntax-1.2.0.dist-info/METADATA
sphinx_syntax-1.2.0.dist-info/WHEEL
sphinx_syntax-1.2.0.dist-info/top_level.txt
sphinx_syntax-1.2.0.dist-info/RECORD
